AUTHORS.rst
CHANGELOG.rst
LICENSE
MANIFEST.in
README.rst
setup.py
django_sitefilter.egg-info/PKG-INFO
django_sitefilter.egg-info/SOURCES.txt
django_sitefilter.egg-info/dependency_links.txt
django_sitefilter.egg-info/not-zip-safe
django_sitefilter.egg-info/requires.txt
django_sitefilter.egg-info/top_level.txt
sitefilter/__init__.py
sitefilter/admin.py
sitefilter/models.py
sitefilter/urls.py
sitefilter/views.py
sitefilter/templates/admin/base.html
sitefilter/templates/sitefilter/sitefilter.html
sitefilter/templatetags/__init__.py
sitefilter/templatetags/sitefilter_tags.py