Metadata-Version: 1.1
Name: django-sitefilter
Version: 0.0.1
Summary: Django app adding a global filter limiting admin content to selected site.
Home-page: http://github.com/praekelt/django-sitefilter
Author: Praekelt Foundation
Author-email: dev@praekeltfoundation.org
License: BSD
Platform: UNKNOWN
Classifier: Programming Language :: Python
Classifier: License :: OSI Approved :: BSD License
Classifier: Development Status :: 4 - Beta
Classifier: Operating System :: OS Independent
Classifier: Framework :: Django
Classifier: Intended Audience :: Developers
Classifier: Topic :: Internet :: WWW/HTTP :: Dynamic Content
